Metadata-Version: 1.0
Name: prob-distributions-22024kk
Version: 0.1
Summary: Gaussian and Binomial distributions
Home-page: UNKNOWN
Author: Kavitha Katiki
Author-email: kkatiki@outlook.com
License: UNKNOWN
Platform: UNKNOWN
